LICENSE
README
ez_setup.py
install.bat
setup.py
install/README
install/soap_meetings.php
install/soap_users.php
pysugar/__init__.py
pysugar/pysugar.py
pysugar/pysugar_version.py
pysugar/sugarobjects.py
pysugar/sugarstore.py
pysugar.egg-info/PKG-INFO
pysugar.egg-info/SOURCES.txt
pysugar.egg-info/dependency_links.txt
pysugar.egg-info/not-zip-safe
pysugar.egg-info/requires.txt
pysugar.egg-info/top_level.txt
