Metadata-Version: 1.0
Name: pysugar
Version: 0.0.6
Summary: Python binding of SugarCRM, that uses the SOAP API provided by SugarCRM
Home-page: UNKNOWN
Author: Florent Aide, Christophe de Vienne
Author-email: florent.aide@gmail.com, cdevienne@alphacent.com
License: PSF
Keywords: Sugar CRM SOAP
Platform: UNKNOWN
Classifier:  
Classifier:  
Classifier:  
Classifier:  
Classifier: D
Classifier: e
Classifier: v
Classifier: e
Classifier: l
Classifier: o
Classifier: p
Classifier: m
Classifier: e
Classifier: n
Classifier: t
Classifier:  
Classifier: S
Classifier: t
Classifier: a
Classifier: t
Classifier: u
Classifier: s
Classifier:  
Classifier: :
Classifier: :
Classifier:  
Classifier: 3
Classifier:  
Classifier: -
Classifier:  
Classifier: A
Classifier: l
Classifier: p
Classifier: h
Classifier: a
Classifier: 
